metriql2metabase/__init__.py
metriql2metabase/dbt_metabase.py
metriql2metabase/metabase.py
metriql2metabase/metadata.py
metriql2metabase/models/__init__.py
metriql2metabase/models/metabase.py
metriql_metabase-0.5.data/scripts/metriql-metabase
metriql_metabase-0.5.dist-info/LICENSE
metriql_metabase-0.5.dist-info/METADATA
metriql_metabase-0.5.dist-info/WHEEL
metriql_metabase-0.5.dist-info/top_level.txt
metriql_metabase-0.5.dist-info/RECORD
