Metadata-Version: 2.1
Name: metriql-metabase
Version: 0.5
Summary: Metriql Metabase integration
Home-page: https://github.com/metriql/metriql-metabase
Author: Burak Emre Kabakci
Author-email: emre@rakam.io
License: MIT License
Platform: UNKNOWN
Classifier: Development Status :: 3 - Alpha
Classifier: Intended Audience :: Developers
Classifier: License :: OSI Approved :: MIT License
Classifier: Operating System :: OS Independent
Classifier: Programming Language :: Python
Classifier: Programming Language :: Python :: 3 :: Only
Classifier: Programming Language :: Python :: 3.6
Classifier: Programming Language :: Python :: 3.7
Classifier: Topic :: Software Development :: Libraries
Classifier: Topic :: Software Development :: Libraries :: Python Modules
License-File: LICENSE
Requires-Dist: requests
Provides-Extra: test
Requires-Dist: requests ; extra == 'test'
